requests_adapter_injector.pth
requests_adapter_injector/__init__.py
requests_adapter_injector/injector.py
requests_adapter_injector/logger.py
requests_adapter_injector/test_adapter.py
requests_adapter_injector-0.0.6.dist-info/LICENSE
requests_adapter_injector-0.0.6.dist-info/METADATA
requests_adapter_injector-0.0.6.dist-info/WHEEL
requests_adapter_injector-0.0.6.dist-info/entry_points.txt
requests_adapter_injector-0.0.6.dist-info/top_level.txt
requests_adapter_injector-0.0.6.dist-info/RECORD
