Metadata-Version: 2.1
Name: requests-adapter-injector
Version: 0.0.6
Summary: A global mechanism for injection of Requests transport adapters
Home-page: https://github.com/kshpytsya/requests-adapter-injector
Author: Kyrylo Shpytsya
Author-email: kshpitsa@gmail.com
License: MIT License
Platform: UNKNOWN
Classifier: License :: OSI Approved :: MIT License
Requires-Python: >=3.6
License-File: LICENSE
Requires-Dist: importhook (<2,>=1.0.8)
Requires-Dist: requests (<3,>=2.23.0)
Requires-Dist: importlib-metadata ; python_version < "3.8"
